pomodorable/__about__.py
pomodorable/__init__.py
pomodorable/__main__.py
pomodorable/about_screen.py
pomodorable/app.tcss
pomodorable/app_config.py
pomodorable/app_data.py
pomodorable/app_utils.py
pomodorable/cli.py
pomodorable/mru_list.py
pomodorable/mru_screen.py
pomodorable/output_csv.py
pomodorable/output_md.py
pomodorable/quit_screen.py
pomodorable/settings_screen.py
pomodorable/timerbar.py
pomodorable/ui.py
pomodorable-0.4.dist-info/METADATA
pomodorable-0.4.dist-info/WHEEL
pomodorable-0.4.dist-info/entry_points.txt
pomodorable-0.4.dist-info/licenses/LICENSE.txt
pomodorable-0.4.dist-info/RECORD
