Metadata-Version: 2.4
Name: pomodorable
Version: 0.4
Summary: A pomodoro timer implemented as a Textual app
Project-URL: Source, https://github.com/wmelvin/pomodorable
Project-URL: Documentation, https://github.com/wmelvin/pomodorable#readme
Author-email: Bill Melvin <bill@billmelvin.com>
License-Expression: MIT
License-File: LICENSE.txt
Keywords: TUI,Textual,pomodoro,pomodoro timer,timer
Classifier: Development Status :: 4 - Beta
Classifier: Programming Language :: Python
Classifier: Programming Language :: Python :: 3.9
Classifier: Programming Language :: Python :: 3.10
Classifier: Programming Language :: Python :: 3.11
Classifier: Programming Language :: Python :: 3.12
Classifier: Programming Language :: Python :: 3.13
Classifier: Programming Language :: Python :: Implementation :: CPython
Classifier: Programming Language :: Python :: Implementation :: PyPy
Requires-Python: >=3.9
Requires-Dist: click==8.1.8
Requires-Dist: linkify-it-py==2.0.3
Requires-Dist: markdown-it-py[linkify,plugins]==3.0.0
Requires-Dist: mdit-py-plugins==0.4.2
Requires-Dist: mdurl==0.1.2
Requires-Dist: platformdirs==4.3.7
Requires-Dist: playsound3==3.2.3
Requires-Dist: plyer==2.1.0
Requires-Dist: pygments==2.19.1
Requires-Dist: python-dotenv==1.1.0
Requires-Dist: rich==14.0.0
Requires-Dist: textual==3.1.0
Requires-Dist: tomlkit==0.13.2
Requires-Dist: typing-extensions==4.13.2
Requires-Dist: uc-micro-py==1.0.3
